menu_system/__init__.py
menu_system/admin.py
menu_system/apps.py
menu_system/context_processors.py
menu_system/models.py
menu_system/tests.py
menu_system/views.py
menu_system/migrations/0001_initial.py
menu_system/migrations/0002_auto_20191119_2234.py
menu_system/migrations/0003_menutop_link_view_path.py
menu_system/migrations/0004_menutop_superuser_only.py
menu_system/migrations/0005_menuapp.py
menu_system/migrations/0006_sociallink.py
menu_system/migrations/0007_sociallink_icon_name.py
menu_system/migrations/0008_delete_websiteinfo.py
menu_system/migrations/0009_auto_20191120_1616.py
menu_system/migrations/0010_userlink.py
menu_system/migrations/0011_auto_20191120_1720.py
menu_system/migrations/0012_userlink_account_req.py
menu_system/migrations/0013_auto_20191120_1848.py
menu_system/migrations/__init__.py
menu_system/static/menu_system/css/materialize.css
menu_system/static/menu_system/css/materialize.min.css
menu_system/static/menu_system/css/menu.css
menu_system/static/menu_system/js/jquery.js
menu_system/static/menu_system/js/materialize.js
menu_system/static/menu_system/js/materialize.min.js
menu_system/static/menu_system/js/menu_system.js
menu_system/templates/menu_system/base.html
menu_system/templates/menu_system/navbar_main.html
django_materialize_menu_system-0.0.1.dist-info/LICENSE
django_materialize_menu_system-0.0.1.dist-info/METADATA
django_materialize_menu_system-0.0.1.dist-info/WHEEL
django_materialize_menu_system-0.0.1.dist-info/top_level.txt
django_materialize_menu_system-0.0.1.dist-info/RECORD
